pyprofiler/__init__.py
pyprofiler/profiler.py
mypyprofiler-0.0.0.dist-info/METADATA
mypyprofiler-0.0.0.dist-info/WHEEL
mypyprofiler-0.0.0.dist-info/top_level.txt
mypyprofiler-0.0.0.dist-info/RECORD
